simulite/__init__.py
simulite/env.py
simulite-1.1.1.dist-info/LICENSE
simulite-1.1.1.dist-info/METADATA
simulite-1.1.1.dist-info/WHEEL
simulite-1.1.1.dist-info/top_level.txt
simulite-1.1.1.dist-info/RECORD
